whotfis_py/__init__.py
whotfis_py/parser.py
whotfis_py/registries.py
whotfis_py/result.py
whotfis_py-0.0.7.dist-info/LICENSE
whotfis_py-0.0.7.dist-info/METADATA
whotfis_py-0.0.7.dist-info/WHEEL
whotfis_py-0.0.7.dist-info/top_level.txt
whotfis_py-0.0.7.dist-info/RECORD
