Metadata-Version: 2.1
Name: whotfis-py
Version: 0.0.7
Summary: Simple package to interact with the whois command line tool
Home-page: https://github.com/xV4L3x/whotfis-py
Author: Valerio Pio De Nicola
Author-email: valeriopio02@gmail.com
License: Apache 2
Keywords: python,whois,whois command line,whois python,whois python package
Classifier: Development Status :: 3 - Alpha
Classifier: Intended Audience :: Developers
Classifier: Programming Language :: Python :: 3
Classifier: Operating System :: MacOS :: MacOS X
License-File: LICENSE
